LICENSE
MANIFEST.in
README.md
package.json
requirements.txt
setup.cfg
setup.py
frodocs_material.egg-info/PKG-INFO
frodocs_material.egg-info/SOURCES.txt
frodocs_material.egg-info/dependency_links.txt
frodocs_material.egg-info/entry_points.txt
frodocs_material.egg-info/not-zip-safe
frodocs_material.egg-info/requires.txt
frodocs_material.egg-info/top_level.txt
material/404.html
material/__init__.py
material/base.html
material/frodocs_theme.yml
material/main.html
material/assets/fonts/font-awesome.css
material/assets/fonts/material-icons.css
material/assets/fonts/specimen/FontAwesome.ttf
material/assets/fonts/specimen/FontAwesome.woff
material/assets/fonts/specimen/FontAwesome.woff2
material/assets/fonts/specimen/MaterialIcons-Regular.ttf
material/assets/fonts/specimen/MaterialIcons-Regular.woff
material/assets/fonts/specimen/MaterialIcons-Regular.woff2
material/assets/images/favicon.png
material/assets/images/icons/bitbucket.1b09e088.svg
material/assets/images/icons/github.f0b8504a.svg
material/assets/images/icons/gitlab.6dd19c00.svg
material/assets/javascripts/application.c33a9706.js
material/assets/javascripts/modernizr.86422ebf.js
material/assets/javascripts/lunr/lunr.ar.js
material/assets/javascripts/lunr/lunr.da.js
material/assets/javascripts/lunr/lunr.de.js
material/assets/javascripts/lunr/lunr.du.js
material/assets/javascripts/lunr/lunr.es.js
material/assets/javascripts/lunr/lunr.fi.js
material/assets/javascripts/lunr/lunr.fr.js
material/assets/javascripts/lunr/lunr.hu.js
material/assets/javascripts/lunr/lunr.it.js
material/assets/javascripts/lunr/lunr.ja.js
material/assets/javascripts/lunr/lunr.jp.js
material/assets/javascripts/lunr/lunr.multi.js
material/assets/javascripts/lunr/lunr.nl.js
material/assets/javascripts/lunr/lunr.no.js
material/assets/javascripts/lunr/lunr.pt.js
material/assets/javascripts/lunr/lunr.ro.js
material/assets/javascripts/lunr/lunr.ru.js
material/assets/javascripts/lunr/lunr.stemmer.support.js
material/assets/javascripts/lunr/lunr.sv.js
material/assets/javascripts/lunr/lunr.th.js
material/assets/javascripts/lunr/lunr.tr.js
material/assets/javascripts/lunr/lunr.vi.js
material/assets/javascripts/lunr/tinyseg.js
material/assets/javascripts/lunr/wordcut.js
