Metadata-Version: 2.1
Name: frodocs-material
Version: 4.6.4
Summary: A Material Design theme for Frodocs
Home-page: https://squidfunk.github.io/frodocs-material/
Author: Martin Donath
Author-email: martin.donath@squidfunk.com
License: MIT
Keywords: frodocs,documentation,theme
Platform: UNKNOWN
Classifier: Development Status :: 5 - Production/Stable
Classifier: License :: OSI Approved :: MIT License
Classifier: Programming Language :: JavaScript
Classifier: Programming Language :: Python
Classifier: Topic :: Documentation
Classifier: Topic :: Text Processing :: Markup :: HTML
